pyrnaither/__init__.py
pyrnaither/__main__.py
pyrnaither/main.py
pyrnaither/data/__init__.py
pyrnaither/data/datasets.py
pyrnaither/logging/__init__.py
pyrnaither/logging/logger.py
pyrnaither/normalization/__init__.py
pyrnaither/normalization/normalizer.py
pyrnaither/pipeline/__init__.py
pyrnaither/pipeline/workflow.py
pyrnaither/stats/__init__.py
pyrnaither/stats/qc.py
pyrnaither/stats/qc_todo.py
pyrnaither/stats/stattests.py
pyrnaither/stats/stattests_todo.py
pyrnaither/utils/__init__.py
pyrnaither/utils/utilities.py
pyrnaither/visualization/__init__.py
pyrnaither/visualization/visualizer.py
pyrnaither-0.0.3.dist-info/licenses/LICENSE
pyrnaither-0.0.3.dist-info/METADATA
pyrnaither-0.0.3.dist-info/WHEEL
pyrnaither-0.0.3.dist-info/entry_points.txt
pyrnaither-0.0.3.dist-info/top_level.txt
pyrnaither-0.0.3.dist-info/RECORD
