Metadata-Version: 2.4
Name: pyRNAither
Version: 0.0.3
Summary: Python reimplementation of RNAither adapted for high-throughput CRISPR screening analysis
Author-email: Rahul Brahma <rahul.brahma@uni-greifswald.de>, Yasas Wijesekara <yasas.wijesekara@uni-greifswald.de>
License-Expression: LicenseRef-LICENSE
Requires-Python: >=3.11
License-File: LICENSE
Requires-Dist: numpy>=2.3.0
Requires-Dist: pandas>=2.3.0
Requires-Dist: matplotlib>=3.0
Requires-Dist: scipy>=1.4
Requires-Dist: scikit-learn
Requires-Dist: matplotlib-venn
Requires-Dist: statsmodels
Requires-Dist: sphinx>=8.2.3
Requires-Dist: sphinx-rtd-theme>=3.0.2
Requires-Dist: sphinx-autodoc-typehints>=3.2.0
Dynamic: license-file
